czml3/__init__.py
czml3/base.py
czml3/common.py
czml3/constants.py
czml3/core.py
czml3/enums.py
czml3/properties.py
czml3/py.typed
czml3/types.py
czml3/widget.py
czml3-3.0.0.dist-info/licenses/LICENSE.txt
czml3-3.0.0.dist-info/METADATA
czml3-3.0.0.dist-info/WHEEL
czml3-3.0.0.dist-info/top_level.txt
czml3-3.0.0.dist-info/RECORD
