Metadata-Version: 2.4
Name: czml3
Version: 3.0.0
Summary: Python 3 library to write CZML
Author-email: Daniel Stoops <danielstoops25@gmail.com>, Juan Luis Cano Rodríguez <hello@juanlu.space>
License: BSD-3-Clause license
Project-URL: Repository, https://github.com/Stoops-ML/czml3
Project-URL: Documentation, https://czml3.readthedocs.io/en
Keywords: czml,cesium
Classifier: Programming Language :: Python
Classifier: Programming Language :: Python :: 3
Classifier: Programming Language :: Python :: 3.10
Classifier: Programming Language :: Python :: 3.11
Classifier: Programming Language :: Python :: 3.12
Classifier: Programming Language :: Python :: 3.13
Classifier: Programming Language :: Python :: Implementation :: CPython
Classifier: Intended Audience :: Education
Classifier: Intended Audience :: Science/Research
Classifier: Operating System :: OS Independent
Classifier: Topic :: Scientific/Engineering
Requires-Python: >=3.10
License-File: LICENSE.txt
Requires-Dist: pydantic>=2.10.1
Requires-Dist: python-dateutil<3,>=2.7
Requires-Dist: typing-extensions>=4.12.0
Requires-Dist: StrEnum>=0.4.0
Requires-Dist: numpy
Provides-Extra: dev
Requires-Dist: build; extra == "dev"
Requires-Dist: pytest; extra == "dev"
Requires-Dist: pytest-cov; extra == "dev"
Requires-Dist: pytest-mypy; extra == "dev"
Requires-Dist: ruff; extra == "dev"
Requires-Dist: tox; extra == "dev"
Requires-Dist: types-python-dateutil; extra == "dev"
Dynamic: license-file
